mabwiser/__init__.py
mabwiser/_version.py
mabwiser/approximate.py
mabwiser/base_mab.py
mabwiser/clusters.py
mabwiser/greedy.py
mabwiser/linear.py
mabwiser/mab.py
mabwiser/neighbors.py
mabwiser/popularity.py
mabwiser/rand.py
mabwiser/simulator.py
mabwiser/softmax.py
mabwiser/thompson.py
mabwiser/treebandit.py
mabwiser/ucb.py
mabwiser/utils.py
mabwiser-2.7.4.dist-info/LICENSE
mabwiser-2.7.4.dist-info/METADATA
mabwiser-2.7.4.dist-info/WHEEL
mabwiser-2.7.4.dist-info/top_level.txt
mabwiser-2.7.4.dist-info/RECORD
