Metadata-Version: 2.1
Name: mabwiser
Version: 2.7.4
Summary: MABWiser: Parallelizable Contextual Multi-Armed Bandits Library
Home-page: https://github.com/fidelity/mabwiser
Author: FMR LLC
Project-URL: Documentation, https://fidelity.github.io/mabwiser/
Project-URL: Source, https://github.com/fidelity/mabwiser
Classifier: License :: OSI Approved :: Apache Software License
Classifier: Programming Language :: Python :: 3.8
Classifier: Operating System :: OS Independent
License-File: LICENSE
Requires-Dist: joblib
Requires-Dist: numpy >=1.17.0
Requires-Dist: pandas
Requires-Dist: scikit-learn >=0.24.0
Requires-Dist: scipy
Requires-Dist: seaborn >=0.9.0
